<?xml version="1.0"?>
<Climate_Strategy>
	<Standart>
		<Prioritet T="50" RH="50"/>
		<Температура_наружная>
			<Влияние_на_температуру Val="2" Rules="1"/>
			<Влияние_на_влажность Val="0" Rules="0"/>
			<Влияние_на_СО2 Val="10" Rules="0"/>
			<Влияние_на_свет Val="0" Rules="0"/>
			<Максимум Val="0" Rules="0"/>
			<Минимум Val="0" Rules="0"/>
			<Оптимум Val="0" Rules="0"/>
			<Важность_оптимум Val="0" Rules="0"/>
			<Время_реакции Val="0" Rules="0"/>
		</Температура_наружная>
		<Скорость_ветра>
			<Влияние_на_температуру Val="-2" Rules="0"/>
			<Влияние_на_влажность Val="0" Rules="0"/>
			<Влияние_на_СО2 Val="9" Rules="0"/>
			<Влияние_на_свет Val="0" Rules="0"/>
			<Максимум Val="0" Rules="0"/>
			<Минимум Val="0" Rules="0"/>
			<Оптимум Val="0" Rules="0"/>
			<Важность_оптимум Val="0" Rules="0"/>
			<Время_реакции Val="0" Rules="0"/>
		</Скорость_ветра>
		<Солнечная_радиация_Средняя>
			<Влияние_на_температуру Val="3" Rules="1"/>
			<Влияние_на_влажность Val="0" Rules="0"/>
			<Влияние_на_СО2 Val="8" Rules="1"/>
			<Влияние_на_свет Val="0" Rules="0"/>
			<Максимум Val="0" Rules="0"/>
			<Минимум Val="0" Rules="0"/>
			<Оптимум Val="0" Rules="0"/>
			<Важность_оптимум Val="0" Rules="0"/>
			<Время_реакции Val="0" Rules="0"/>
		</Солнечная_радиация_Средняя>
		<Положение_ЭКРАНА>
			<Влияние_на_температуру Val="4" Rules="0"/>
			<Влияние_на_влажность Val="0" Rules="0"/>
			<Влияние_на_СО2 Val="7" Rules="0"/>
			<Влияние_на_свет Val="0" Rules="0"/>
			<Максимум Val="0" Rules="0"/>
			<Минимум Val="0" Rules="0"/>
			<Оптимум Val="0" Rules="0"/>
			<Важность_оптимум Val="0" Rules="0"/>
			<Время_реакции Val="0" Rules="0"/>
		</Положение_ЭКРАНА>
		<Температура_стекла>
			<Влияние_на_температуру Val="5" Rules="1"/>
			<Влияние_на_влажность Val="-1" Rules="0"/>
			<Влияние_на_СО2 Val="6" Rules="0"/>
			<Влияние_на_свет Val="0" Rules="0"/>
			<Максимум Val="0" Rules="0"/>
			<Минимум Val="0" Rules="0"/>
			<Оптимум Val="0" Rules="0"/>
			<Важность_оптимум Val="0" Rules="0"/>
			<Время_реакции Val="0" Rules="0"/>
		</Температура_стекла>
		<Состояние_досветки>
			<Влияние_на_температуру Val="6" Rules="0"/>
			<Влияние_на_влажность Val="0" Rules="0"/>
			<Влияние_на_СО2 Val="5" Rules="0"/>
			<Влияние_на_свет Val="0" Rules="0"/>
			<Максимум Val="0" Rules="0"/>
			<Минимум Val="0" Rules="0"/>
			<Оптимум Val="0" Rules="0"/>
			<Важность_оптимум Val="0" Rules="0"/>
			<Время_реакции Val="0" Rules="0"/>
		</Состояние_досветки>
		<Контур_1_-_Т_воды>
			<Влияние_на_температуру Val="7" Rules="1"/>
			<Влияние_на_влажность Val="2" Rules="1"/>
			<Влияние_на_СО2 Val="0" Rules="0"/>
			<Влияние_на_свет Val="0" Rules="0"/>
			<Максимум Val="90" Rules="1"/>
			<Минимум Val="10" Rules="1"/>
			<Оптимум Val="40" Rules="1"/>
			<Важность_оптимум Val="0" Rules="0"/>
			<Время_реакции Val="0,23" Rules="1"/>
		</Контур_1_-_Т_воды>
		<Контур_2_-_Температура_воды>
			<Влияние_на_температуру Val="7" Rules="0"/>
			<Влияние_на_влажность Val="0" Rules="0"/>
			<Влияние_на_СО2 Val="4" Rules="0"/>
			<Влияние_на_свет Val="0" Rules="0"/>
			<Максимум Val="0" Rules="0"/>
			<Минимум Val="0" Rules="0"/>
			<Оптимум Val="0" Rules="0"/>
			<Важность_оптимум Val="0" Rules="0"/>
			<Время_реакции Val="0" Rules="0"/>
		</Контур_2_-_Температура_воды>
		<Контур_3_-_Температура_воды>
			<Влияние_на_температуру Val="8" Rules="0"/>
			<Влияние_на_влажность Val="0" Rules="0"/>
			<Влияние_на_СО2 Val="3" Rules="0"/>
			<Влияние_на_свет Val="0" Rules="0"/>
			<Максимум Val="0" Rules="0"/>
			<Минимум Val="0" Rules="0"/>
			<Оптимум Val="0" Rules="0"/>
			<Важность_оптимум Val="0" Rules="0"/>
			<Время_реакции Val="0" Rules="0"/>
		</Контур_3_-_Температура_воды>
		<Контур_4_-_Температура_воды>
			<Влияние_на_температуру Val="9" Rules="0"/>
			<Влияние_на_влажность Val="0" Rules="0"/>
			<Влияние_на_СО2 Val="2" Rules="0"/>
			<Влияние_на_свет Val="0" Rules="0"/>
			<Максимум Val="0" Rules="0"/>
			<Минимум Val="0" Rules="0"/>
			<Оптимум Val="0" Rules="0"/>
			<Важность_оптимум Val="0" Rules="0"/>
			<Время_реакции Val="0" Rules="0"/>
		</Контур_4_-_Температура_воды>
		<Контур_5_-_Температура_воды>
			<Влияние_на_температуру Val="10" Rules="0"/>
			<Влияние_на_влажность Val="0" Rules="0"/>
			<Влияние_на_СО2 Val="1" Rules="0"/>
			<Влияние_на_свет Val="0" Rules="0"/>
			<Максимум Val="0" Rules="0"/>
			<Минимум Val="0" Rules="0"/>
			<Оптимум Val="0" Rules="0"/>
			<Важность_оптимум Val="0" Rules="0"/>
			<Время_реакции Val="0" Rules="0"/>
		</Контур_5_-_Температура_воды>
		<HotCorrect>
			<HotPar1 Par="45" Val="2" Rules="201"/>
			<HotPar2 Par="46" Val="3" Rules="102"/>
		</HotCorrect>
		<Rules>
			<Rule1 Par="1" XA="3" YA="1" XB="200" YB="0"/>
			<Rule2 Par="2" XA="3" YA="1" XB="400" YB="2"/>
		</Rules>
		<Средняя_солнечная_радиация><Влияние_на_температуру Val="0" Rules="0"/><Влияние_на_влажность Val="0" Rules="0"/><Влияние_на_СО2 Val="0" Rules="0"/><Влияние_на_свет Val="0" Rules="0"/><Максимум Val="0" Rules="0"/><Минимум Val="0" Rules="0"/><Оптимум Val="0" Rules="0"/><Важность_оптимум Val="0" Rules="0"/><Время_реакции Val="0" Rules="0"/></Средняя_солнечная_радиация><Контур_2_-_Т_воды><Влияние_на_температуру Val="0" Rules="0"/><Влияние_на_влажность Val="0" Rules="0"/><Влияние_на_СО2 Val="0" Rules="0"/><Влияние_на_свет Val="0" Rules="0"/><Максимум Val="80" Rules="0"/><Минимум Val="5" Rules="0"/><Оптимум Val="33" Rules="0"/><Важность_оптимум Val="0" Rules="0"/><Время_реакции Val="0" Rules="0"/></Контур_2_-_Т_воды><Наветренные_фрамуги><Влияние_на_температуру Val="0" Rules="0"/><Влияние_на_влажность Val="0" Rules="0"/><Влияние_на_СО2 Val="0" Rules="0"/><Влияние_на_свет Val="0" Rules="0"/><Максимум Val="60" Rules="0"/><Минимум Val="0" Rules="0"/><Оптимум Val="0" Rules="0"/><Важность_оптимум Val="0" Rules="0"/><Время_реакции Val="0" Rules="0"/></Наветренные_фрамуги><Ultra_Clim_смеситель><Влияние_на_температуру Val="0" Rules="0"/><Влияние_на_влажность Val="0" Rules="0"/><Влияние_на_СО2 Val="0" Rules="0"/><Влияние_на_свет Val="0" Rules="0"/><Максимум Val="0" Rules="0"/><Минимум Val="0" Rules="0"/><Оптимум Val="0" Rules="0"/><Важность_оптимум Val="0" Rules="0"/><Время_реакции Val="0" Rules="0"/></Ultra_Clim_смеситель><Ultra_Clim_вентилятор><Влияние_на_температуру Val="0" Rules="0"/><Влияние_на_влажность Val="0" Rules="0"/><Влияние_на_СО2 Val="0" Rules="0"/><Влияние_на_свет Val="0" Rules="0"/><Максимум Val="50" Rules="0"/><Минимум Val="30" Rules="0"/><Оптимум Val="0" Rules="0"/><Важность_оптимум Val="0" Rules="0"/><Время_реакции Val="0" Rules="0"/></Ultra_Clim_вентилятор><Ultra_Clim_подогрев><Влияние_на_температуру Val="0" Rules="0"/><Влияние_на_влажность Val="0" Rules="0"/><Влияние_на_СО2 Val="0" Rules="0"/><Влияние_на_свет Val="0" Rules="0"/><Максимум Val="23" Rules="0"/><Минимум Val="3" Rules="0"/><Оптимум Val="22" Rules="0"/><Важность_оптимум Val="0" Rules="0"/><Время_реакции Val="0" Rules="0"/></Ultra_Clim_подогрев></Standart>
	<Бархатный_вечер><Prioritet T="50" RH="50"/><Температура_наружная><Влияние_на_температуру Val="1" Rules="0"/><Влияние_на_влажность Val="0" Rules="0"/><Влияние_на_СО2 Val="10" Rules="0"/><Влияние_на_свет Val="0" Rules="0"/><Максимум Val="0" Rules="0"/><Минимум Val="0" Rules="0"/><Оптимум Val="0" Rules="0"/><Важность_оптимум Val="0" Rules="0"/><Время_реакции Val="0" Rules="0"/></Температура_наружная><Скорость_ветра><Влияние_на_температуру Val="2" Rules="0"/><Влияние_на_влажность Val="0" Rules="0"/><Влияние_на_СО2 Val="9" Rules="0"/><Влияние_на_свет Val="0" Rules="0"/><Максимум Val="0" Rules="0"/><Минимум Val="0" Rules="0"/><Оптимум Val="0" Rules="0"/><Важность_оптимум Val="0" Rules="0"/><Время_реакции Val="0" Rules="0"/></Скорость_ветра><Солнечная_радиация_Средняя><Влияние_на_температуру Val="3" Rules="0"/><Влияние_на_влажность Val="0" Rules="0"/><Влияние_на_СО2 Val="8" Rules="0"/><Влияние_на_свет Val="0" Rules="0"/><Максимум Val="0" Rules="0"/><Минимум Val="0" Rules="0"/><Оптимум Val="0" Rules="0"/><Важность_оптимум Val="0" Rules="0"/><Время_реакции Val="0" Rules="0"/></Солнечная_радиация_Средняя><Положение_ЭКРАНА><Влияние_на_температуру Val="4" Rules="0"/><Влияние_на_влажность Val="0" Rules="0"/><Влияние_на_СО2 Val="7" Rules="0"/><Влияние_на_свет Val="0" Rules="0"/><Максимум Val="0" Rules="0"/><Минимум Val="0" Rules="0"/><Оптимум Val="0" Rules="0"/><Важность_оптимум Val="0" Rules="0"/><Время_реакции Val="0" Rules="0"/></Положение_ЭКРАНА><Температура_стекла><Влияние_на_температуру Val="5" Rules="0"/><Влияние_на_влажность Val="0" Rules="0"/><Влияние_на_СО2 Val="6" Rules="0"/><Влияние_на_свет Val="0" Rules="0"/><Максимум Val="0" Rules="0"/><Минимум Val="0" Rules="0"/><Оптимум Val="0" Rules="0"/><Важность_оптимум Val="0" Rules="0"/><Время_реакции Val="0" Rules="0"/></Температура_стекла><Состояние_досветки><Влияние_на_температуру Val="6" Rules="0"/><Влияние_на_влажность Val="0" Rules="0"/><Влияние_на_СО2 Val="5" Rules="0"/><Влияние_на_свет Val="0" Rules="0"/><Максимум Val="0" Rules="0"/><Минимум Val="0" Rules="0"/><Оптимум Val="0" Rules="0"/><Важность_оптимум Val="0" Rules="0"/><Время_реакции Val="0" Rules="0"/></Состояние_досветки><Контур_1_-_Т_воды><Влияние_на_температуру Val="0" Rules="0"/><Влияние_на_влажность Val="0" Rules="0"/><Влияние_на_СО2 Val="0" Rules="0"/><Влияние_на_свет Val="0" Rules="0"/><Максимум Val="0" Rules="0"/><Минимум Val="0" Rules="0"/><Оптимум Val="0" Rules="0"/><Важность_оптимум Val="0" Rules="0"/><Время_реакции Val="0" Rules="0"/></Контур_1_-_Т_воды><Контур_2_-_Температура_воды><Влияние_на_температуру Val="7" Rules="0"/><Влияние_на_влажность Val="0" Rules="0"/><Влияние_на_СО2 Val="4" Rules="0"/><Влияние_на_свет Val="0" Rules="0"/><Максимум Val="0" Rules="0"/><Минимум Val="0" Rules="0"/><Оптимум Val="0" Rules="0"/><Важность_оптимум Val="0" Rules="0"/><Время_реакции Val="0" Rules="0"/></Контур_2_-_Температура_воды><Контур_3_-_Температура_воды><Влияние_на_температуру Val="8" Rules="0"/><Влияние_на_влажность Val="0" Rules="0"/><Влияние_на_СО2 Val="3" Rules="0"/><Влияние_на_свет Val="0" Rules="0"/><Максимум Val="0" Rules="0"/><Минимум Val="0" Rules="0"/><Оптимум Val="0" Rules="0"/><Важность_оптимум Val="0" Rules="0"/><Время_реакции Val="0" Rules="0"/></Контур_3_-_Температура_воды><Контур_4_-_Температура_воды><Влияние_на_температуру Val="9" Rules="0"/><Влияние_на_влажность Val="0" Rules="0"/><Влияние_на_СО2 Val="2" Rules="0"/><Влияние_на_свет Val="0" Rules="0"/><Максимум Val="0" Rules="0"/><Минимум Val="0" Rules="0"/><Оптимум Val="0" Rules="0"/><Важность_оптимум Val="0" Rules="0"/><Время_реакции Val="0" Rules="0"/></Контур_4_-_Температура_воды><Контур_5_-_Температура_воды><Влияние_на_температуру Val="10" Rules="0"/><Влияние_на_влажность Val="0" Rules="0"/><Влияние_на_СО2 Val="1" Rules="0"/><Влияние_на_свет Val="0" Rules="0"/><Максимум Val="0" Rules="0"/><Минимум Val="0" Rules="0"/><Оптимум Val="0" Rules="0"/><Важность_оптимум Val="0" Rules="0"/><Время_реакции Val="0" Rules="0"/></Контур_5_-_Температура_воды><HotCorrect><HotPar1 Par="45" Val="2" Rules="201"/><HotPar2 Par="46" Val="4" Rules="102"/></HotCorrect><Rules><Rule1 Par="1" XA="3" YA="1" XB="200" YB="0"/><Rule2 Par="2" XA="3" YA="1" XB="400" YB="2"/></Rules></Бархатный_вечер><Зимнее_утро><Prioritet T="50" RH="50"/><Температура_наружная><Влияние_на_температуру Val="1" Rules="0"/><Влияние_на_влажность Val="0" Rules="0"/><Влияние_на_СО2 Val="10" Rules="0"/><Влияние_на_свет Val="0" Rules="0"/><Максимум Val="0" Rules="0"/><Минимум Val="0" Rules="0"/><Оптимум Val="0" Rules="0"/><Важность_оптимум Val="0" Rules="0"/><Время_реакции Val="0" Rules="0"/></Температура_наружная><Скорость_ветра><Влияние_на_температуру Val="2" Rules="0"/><Влияние_на_влажность Val="0" Rules="0"/><Влияние_на_СО2 Val="9" Rules="0"/><Влияние_на_свет Val="0" Rules="0"/><Максимум Val="0" Rules="0"/><Минимум Val="0" Rules="0"/><Оптимум Val="0" Rules="0"/><Важность_оптимум Val="0" Rules="0"/><Время_реакции Val="0" Rules="0"/></Скорость_ветра><Солнечная_радиация_Средняя><Влияние_на_температуру Val="3" Rules="0"/><Влияние_на_влажность Val="0" Rules="0"/><Влияние_на_СО2 Val="8" Rules="0"/><Влияние_на_свет Val="0" Rules="0"/><Максимум Val="0" Rules="0"/><Минимум Val="0" Rules="0"/><Оптимум Val="0" Rules="0"/><Важность_оптимум Val="0" Rules="0"/><Время_реакции Val="0" Rules="0"/></Солнечная_радиация_Средняя><Положение_ЭКРАНА><Влияние_на_температуру Val="4" Rules="0"/><Влияние_на_влажность Val="0" Rules="0"/><Влияние_на_СО2 Val="7" Rules="0"/><Влияние_на_свет Val="0" Rules="0"/><Максимум Val="0" Rules="0"/><Минимум Val="0" Rules="0"/><Оптимум Val="0" Rules="0"/><Важность_оптимум Val="0" Rules="0"/><Время_реакции Val="0" Rules="0"/></Положение_ЭКРАНА><Температура_стекла><Влияние_на_температуру Val="5" Rules="0"/><Влияние_на_влажность Val="0" Rules="0"/><Влияние_на_СО2 Val="6" Rules="0"/><Влияние_на_свет Val="0" Rules="0"/><Максимум Val="0" Rules="0"/><Минимум Val="0" Rules="0"/><Оптимум Val="0" Rules="0"/><Важность_оптимум Val="0" Rules="0"/><Время_реакции Val="0" Rules="0"/></Температура_стекла><Состояние_досветки><Влияние_на_температуру Val="6" Rules="0"/><Влияние_на_влажность Val="0" Rules="0"/><Влияние_на_СО2 Val="5" Rules="0"/><Влияние_на_свет Val="0" Rules="0"/><Максимум Val="0" Rules="0"/><Минимум Val="0" Rules="0"/><Оптимум Val="0" Rules="0"/><Важность_оптимум Val="0" Rules="0"/><Время_реакции Val="0" Rules="0"/></Состояние_досветки><Контур_1_-_Т_воды><Влияние_на_температуру Val="0" Rules="0"/><Влияние_на_влажность Val="0" Rules="0"/><Влияние_на_СО2 Val="0" Rules="0"/><Влияние_на_свет Val="0" Rules="0"/><Максимум Val="0" Rules="0"/><Минимум Val="0" Rules="0"/><Оптимум Val="0" Rules="0"/><Важность_оптимум Val="0" Rules="0"/><Время_реакции Val="0" Rules="0"/></Контур_1_-_Т_воды><Контур_2_-_Температура_воды><Влияние_на_температуру Val="7" Rules="0"/><Влияние_на_влажность Val="0" Rules="0"/><Влияние_на_СО2 Val="4" Rules="0"/><Влияние_на_свет Val="0" Rules="0"/><Максимум Val="0" Rules="0"/><Минимум Val="0" Rules="0"/><Оптимум Val="0" Rules="0"/><Важность_оптимум Val="0" Rules="0"/><Время_реакции Val="0" Rules="0"/></Контур_2_-_Температура_воды><Контур_3_-_Температура_воды><Влияние_на_температуру Val="8" Rules="0"/><Влияние_на_влажность Val="0" Rules="0"/><Влияние_на_СО2 Val="3" Rules="0"/><Влияние_на_свет Val="0" Rules="0"/><Максимум Val="0" Rules="0"/><Минимум Val="0" Rules="0"/><Оптимум Val="0" Rules="0"/><Важность_оптимум Val="0" Rules="0"/><Время_реакции Val="0" Rules="0"/></Контур_3_-_Температура_воды><Контур_4_-_Температура_воды><Влияние_на_температуру Val="9" Rules="0"/><Влияние_на_влажность Val="0" Rules="0"/><Влияние_на_СО2 Val="2" Rules="0"/><Влияние_на_свет Val="0" Rules="0"/><Максимум Val="0" Rules="0"/><Минимум Val="0" Rules="0"/><Оптимум Val="0" Rules="0"/><Важность_оптимум Val="0" Rules="0"/><Время_реакции Val="0" Rules="0"/></Контур_4_-_Температура_воды><Контур_5_-_Температура_воды><Влияние_на_температуру Val="10" Rules="0"/><Влияние_на_влажность Val="0" Rules="0"/><Влияние_на_СО2 Val="1" Rules="0"/><Влияние_на_свет Val="0" Rules="0"/><Максимум Val="0" Rules="0"/><Минимум Val="0" Rules="0"/><Оптимум Val="0" Rules="0"/><Важность_оптимум Val="0" Rules="0"/><Время_реакции Val="0" Rules="0"/></Контур_5_-_Температура_воды><HotCorrect><HotPar1 Par="45" Val="2" Rules="201"/><HotPar2 Par="46" Val="4" Rules="102"/></HotCorrect><Rules><Rule1 Par="1" XA="3" YA="1" XB="200" YB="0"/><Rule2 Par="2" XA="1" YA="0,5" XB="400" YB="2"/></Rules></Зимнее_утро></Climate_Strategy>
